freeact/__init__.py
freeact/cli.py
freeact/permissions.py
freeact/agent/__init__.py
freeact/agent/core.py
freeact/agent/config/__init__.py
freeact/agent/config/config.py
freeact/agent/config/init.py
freeact/agent/config/templates/servers.json
freeact/agent/config/templates/prompts/system.md
freeact/agent/config/templates/skills/output-parsers/SKILL.md
freeact/agent/config/templates/skills/saving-codeacts/SKILL.md
freeact/agent/config/templates/skills/task-planning/SKILL.md
freeact/agent/tools/__init__.py
freeact/agent/tools/gsearch.py
freeact/agent/tools/ipybox.json
freeact/agent/tools/utils.py
freeact/agent/tools/pytools/__init__.py
freeact/agent/tools/pytools/apigen.py
freeact/agent/tools/pytools/categories.py
freeact/agent/tools/pytools/search.py
freeact/terminal/__init__.py
freeact/terminal/completion.py
freeact/terminal/display.py
freeact/terminal/images.py
freeact/terminal/interface.py
freeact/terminal/prompt.py
freeact/terminal/recording.py
freeact-0.7.0.dist-info/METADATA
freeact-0.7.0.dist-info/WHEEL
freeact-0.7.0.dist-info/entry_points.txt
freeact-0.7.0.dist-info/licenses/LICENSE
freeact-0.7.0.dist-info/RECORD
