Metadata-Version: 2.4
Name: freeact
Version: 0.7.0
Summary: Freeact code action agent
Author-email: Martin Krasser <martin@gradion.ai>
License-Expression: Apache-2.0
License-File: LICENSE
Requires-Python: <3.15,>=3.11
Requires-Dist: aiofiles>=25.1.0
Requires-Dist: aiostream>=0.7.1
Requires-Dist: google-genai>=1.56.0
Requires-Dist: ipybox>=0.7.2
Requires-Dist: pillow>=12.0.0
Requires-Dist: prompt-toolkit>=3.0.0
Requires-Dist: pydantic-ai>=1.36.0
Requires-Dist: python-dotenv>=1.0.0
Requires-Dist: pyyaml>=6.0.3
Requires-Dist: rich>=14.2.0
